geneplexus/__init__.py
geneplexus/_geneplexus.py
geneplexus/cli.py
geneplexus/download.py
geneplexus/exception.py
geneplexus/geneplexus.py
geneplexus/util.py
geneplexus/_clustering/__init__.py
geneplexus/_clustering/domino.py
geneplexus/_clustering/domino_utls.py
geneplexus/_clustering/louvain.py
geneplexus/_config/__init__.py
geneplexus/_config/config.py
geneplexus/_config/logger_util.py
geneplexus-3.0.0.dist-info/METADATA
geneplexus-3.0.0.dist-info/WHEEL
geneplexus-3.0.0.dist-info/entry_points.txt
geneplexus-3.0.0.dist-info/top_level.txt
geneplexus-3.0.0.dist-info/RECORD
