Metadata-Version: 2.4
Name: geneplexus
Version: 3.0.0
Summary: Network based gene classification
Home-page: https://github.com/krishnanlab/PyGenePlexus
Author: Remy Liu and Christopher A. Mancuso
Author-email: renmingl@andrew.cmu.edu, CHRISTOPHER.A.MANCUSO@CUANSCHUTZ.EDU
License: BSD 3-Clause License
Project-URL: Documentation, https://pygeneplexus.readthedocs.io
Keywords: Network Biology,Supervised Learning,Gene Classification
Classifier: Development Status :: 4 - Beta
Classifier: Programming Language :: Python
Classifier: Programming Language :: Python :: 3.10
Classifier: Programming Language :: Python :: 3.11
Classifier: Programming Language :: Python :: 3.12
Classifier: Programming Language :: Python :: 3.13
Classifier: Programming Language :: Python :: 3 :: Only
Classifier: License :: OSI Approved :: BSD License
Requires-Python: >=3.10
Requires-Dist: numpy>=1.20.1
Requires-Dist: scikit-learn>=1.0.0
Requires-Dist: scipy>=1.6.2
Requires-Dist: pandas>=1.2.4
Requires-Dist: networkx>=3.2
Requires-Dist: statsmodels>=0.14.0
Requires-Dist: pcst-fast>=1.0.7
Requires-Dist: requests
Requires-Dist: tqdm
Requires-Dist: pystow
Requires-Dist: pyyaml
Provides-Extra: dev
Requires-Dist: parameterized; extra == "dev"
Requires-Dist: pytest; extra == "dev"
Requires-Dist: pytest-cov; extra == "dev"
Requires-Dist: pytest-mock; extra == "dev"
Requires-Dist: pytest-order; extra == "dev"
Requires-Dist: requests-mock; extra == "dev"
Requires-Dist: tox; extra == "dev"
